{
  "@type" : "TEMPLATE",
  "uid" : "b7f992a5-9740-47b8-ac42-b4f1d7e3293f",
  "description" : {
    "@type" : "RESOURCE_DESCRIPTION",
    "originalAuthor" : {
      "name" : "Erik Sundvall",
      "organisation" : "Region Östergötland & Linköping University, Sweden",
      "email" : "erik.sundvall@regionostergotland.se",
      "date" : "2021-10-25"
    },
    "otherContributors" : [ ],
    "lifecycleState" : {
      "codeString" : "unmanaged"
    },
    "ipAcknowledgements" : { },
    "references" : { },
    "conversionDetails" : { },
    "otherDetails" : {
      "licence" : "",
      "custodian_organisation" : "",
      "original_namespace" : "",
      "original_publisher" : "",
      "custodian_namespace" : "",
      "sem_ver" : "0.1.0",
      "build_uid" : "4845b50b-140d-4f77-8515-8ed351912623",
      "MD5-CAM-1.0.1" : "53c2fcda9105cbacced6508019e9c946",
      "PARENT:MD5-CAM-1.0.1" : "05F3E1D9A0891A37F1DD10A47CCFA472"
    },
    "details" : {
      "nb" : {
        "@type" : "RESOURCE_DESCRIPTION_ITEM",
        "language" : {
          "terminologyId" : {
            "value" : "ISO_639-1"
          },
          "codeString" : "nb"
        },
        "keywords" : [ ],
        "originalResourceUri" : { },
        "otherDetails" : { }
      },
      "pt-br" : {
        "@type" : "RESOURCE_DESCRIPTION_ITEM",
        "language" : {
          "terminologyId" : {
            "value" : "ISO_639-1"
          },
          "codeString" : "pt-br"
        },
        "keywords" : [ ],
        "originalResourceUri" : { },
        "otherDetails" : { }
      },
      "en" : {
        "@type" : "RESOURCE_DESCRIPTION_ITEM",
        "language" : {
          "terminologyId" : {
            "value" : "ISO_639-1"
          },
          "codeString" : "en"
        },
        "keywords" : [ ],
        "originalResourceUri" : { },
        "otherDetails" : { }
      },
      "es" : {
        "@type" : "RESOURCE_DESCRIPTION_ITEM",
        "language" : {
          "terminologyId" : {
            "value" : "ISO_639-1"
          },
          "codeString" : "es"
        },
        "keywords" : [ ],
        "originalResourceUri" : { },
        "otherDetails" : { }
      }
    }
  },
  "parentArchetypeId" : "openEHR-EHR-COMPOSITION.health_summary.v1",
  "differential" : true,
  "archetypeId" : {
    "@type" : "ARCHETYPE_HRID",
    "value" : "openEHR-EHR-COMPOSITION.t_health_summary.v1"
  },
  "definition" : {
    "@type" : "C_COMPLEX_OBJECT",
    "rmTypeName" : "COMPOSITION",
    "nodeId" : "at0000.1",
    "attributes" : [ {
      "@type" : "C_ATTRIBUTE",
      "rmAttributeName" : "context",
      "children" : [ {
        "@type" : "C_COMPLEX_OBJECT",
        "rmTypeName" : "EVENT_CONTEXT",
        "attributes" : [ ],
        "attributeTuples" : [ ]
      } ]
    } ],
    "attributeTuples" : [ ]
  },
  "terminology" : {
    "@type" : "ARCHETYPE_TERMINOLOGY",
    "conceptCode" : "at0000",
    "termDefinitions" : {
      "en" : {
        "at0000.1" : {
          "@type" : "ARCHETYPE_TERM",
          "code" : "at0000.1",
          "text" : "Symptomkontroll-ES-experiment",
          "description" : "Generic document containing a summary of health information about an individual."
        }
      },
      "nb" : {
        "at0000.1" : {
          "@type" : "ARCHETYPE_TERM",
          "code" : "at0000.1",
          "text" : "Symptomkontroll-ES-experiment",
          "description" : "Generisk dokument som inneholder sammendrag av helseinformasjon om et individ."
        }
      },
      "es" : {
        "at0000.1" : {
          "@type" : "ARCHETYPE_TERM",
          "code" : "at0000.1",
          "text" : "Symptomkontroll-ES-experiment",
          "description" : "Documento genérico que contiene un resumen de la información de salud sobre un individuo."
        }
      },
      "pt-br" : {
        "at0000.1" : {
          "@type" : "ARCHETYPE_TERM",
          "code" : "at0000.1",
          "text" : "Symptomkontroll-ES-experiment",
          "description" : "Documento genérico contendo um sumário das informações de saúde sobre um indivíduo."
        }
      }
    },
    "termBindings" : { },
    "terminologyExtracts" : { },
    "valueSets" : { }
  },
  "adlVersion" : "1.4",
  "buildUid" : "1bb01a0c-b737-3322-8eed-9cd204cdc3c0",
  "rmName" : "openehr",
  "rmRelease" : "1.1.0",
  "generated" : true,
  "templateId" : "Symptomkontroll-ES-experiment",
  "otherMetaData" : { },
  "templateOverlays" : [ ],
  "originalLanguage" : {
    "terminologyId" : {
      "value" : "ISO_639-1"
    },
    "codeString" : "en"
  },
  "translations" : [ {
    "@type" : "TRANSLATION_DETAILS",
    "language" : {
      "terminologyId" : {
        "value" : "ISO_639-1"
      },
      "codeString" : "nb"
    },
    "author" : { },
    "otherDetails" : { }
  }, {
    "@type" : "TRANSLATION_DETAILS",
    "language" : {
      "terminologyId" : {
        "value" : "ISO_639-1"
      },
      "codeString" : "pt-br"
    },
    "author" : { },
    "otherDetails" : { }
  }, {
    "@type" : "TRANSLATION_DETAILS",
    "language" : {
      "terminologyId" : {
        "value" : "ISO_639-1"
      },
      "codeString" : "es"
    },
    "author" : { },
    "otherDetails" : { }
  } ]
}